verilog/counter.v
module counter (
    input clk,
    input rst,
    output reg [3:0] count
);
    always @(posedge clk or posedge rst) begin
        if (rst)
            count <= 4'b0000;
        else
            count <= count + 1;
    end
endmodule

verilog/tb_counter.v
`timescale 1ns/1ns

module tb_counter;
    reg clk;
    reg rst;
    wire [3:0] count;

    // 呼叫你的電路 (Instantiate)
    counter uut (
        .clk(clk),
        .rst(rst),
        .count(count)
    );

    // 產生時脈 (Clock)
    initial begin
        clk = 0;
        forever #5 clk = ~clk; // 每 5ns 翻轉一次
    end

    // 測試流程
    initial begin
        // --- 關鍵設定：告訴模擬器要把波形存下來 ---
        $dumpfile("waveform.vcd"); // 檔案名稱叫 waveform.vcd
        $dumpvars(0, tb_counter);  // 紀錄 tb_counter 裡面的所有變數
        // ---------------------------------------

        rst = 1;       // 一開始重置
        #10 rst = 0;   // 10ns 後放開重置
        #100;          // 跑個 100ns
        $finish;       // 結束模擬
    end
endmodule

verilog/waveform.vcd
$date
	Thu Dec 11 08:58:03 2025
$end
$version
	Icarus Verilog
$end
$timescale
	1ns
$end
$scope module tb_counter $end
$var wire 4 ! count [3:0] $end
$var reg 1 " clk $end
$var reg 1 # rst $end
$scope module uut $end
$var wire 1 " clk $end
$var wire 1 # rst $end
$var reg 4 $ count [3:0] $end
$upscope $end
$upscope $end
$enddefinitions $end
$comment Show the parameter values. $end
$dumpall
$end
#0
$dumpvars
b0 $
1#
0"
b0 !
$end
#5
1"
#10
0"
0#
#15
b1 !
b1 $
1"
#20
0"
#25
b10 !
b10 $
1"
#30
0"
#35
b11 !
b11 $
1"
#40
0"
#45
b100 !
b100 $
1"
#50
0"
#55
b101 !
b101 $
1"
#60
0"
#65
b110 !
b110 $
1"
#70
0"
#75
b111 !
b111 $
1"
#80
0"
#85
b1000 !
b1000 $
1"
#90
0"
#95
b1001 !
b1001 $
1"
#100
0"
#105
b1010 !
b1010 $
1"
