HEXBS/me_hexbs_top.v
// ============================================================================
// File Name: ME_HEXBS.v
// Author: HSUN's AI Assistant
// Description: Hexagon-Based Search (HEXBS) Motion Estimation Accelerator
//              Fixed: Added reset logic for cand_x/cand_y to prevent 'X' propagation
// ============================================================================

module ME_HEXBS (
    input  wire         clk,        // 時脈
    input  wire         rst_n,      // 重置訊號 (低電位重置)
    input  wire         i_start,    // 啟動訊號

    // --- 虛擬記憶體介面 ---
    output wire [5:0]   o_cur_x,    
    output wire [5:0]   o_cur_y,    
    input  wire [7:0]   i_cur_pixel,

    output wire [11:0]  o_ref_x,    
    output wire [11:0]  o_ref_y,    
    input  wire [7:0]   i_ref_pixel,

    // --- 輸出結果 ---
    output reg  signed [5:0] o_mv_x,    
    output reg  signed [5:0] o_mv_y,    
    output reg  [15:0]       o_min_sad, 
    output reg               o_done     
);

    // =========================================================
    // 1. 參數與變數
    // =========================================================
    localparam S_IDLE       = 4'd0; 
    localparam S_INIT_00    = 4'd1; 
    localparam S_LHP_PICK   = 4'd2; 
    localparam S_LHP_CALC   = 4'd3; 
    localparam S_LHP_DECIDE = 4'd4; 
    localparam S_SHP_PICK   = 4'd5; 
    localparam S_SHP_CALC   = 4'd6; 
    localparam S_DONE       = 4'd7; 

    reg [3:0]  state, next_state;

    // 搜尋中心與候選點
    reg signed [5:0] center_x, center_y;    
    reg signed [5:0] cand_x, cand_y;        // [Bug Fix] 這裡原本沒 Reset
    
    reg [15:0] global_min_sad;              
    reg signed [5:0] best_vec_x, best_vec_y;

    reg [4:0]  pixel_cnt_x; 
    reg [4:0]  pixel_cnt_y; 
    reg [15:0] current_accum_sad; 

    reg [2:0]  point_idx;   

    // =========================================================
    // 2. 函數與 FSM
    // =========================================================
    function [7:0] abs_diff;
        input [7:0] a, b;
        begin
            abs_diff = (a > b) ? (a - b) : (b - a);
        end
    endfunction

    always @(posedge clk or negedge rst_n) begin
        if (!rst_n) state <= S_IDLE;
        else        state <= next_state;
    end

    always @(*) begin
        case (state)
            S_IDLE:       next_state = i_start ? S_INIT_00 : S_IDLE;
            S_INIT_00:    next_state = (pixel_cnt_x == 15 && pixel_cnt_y == 15) ? S_LHP_PICK : S_INIT_00;
            S_LHP_PICK:   next_state = S_LHP_CALC;
            S_LHP_CALC:   begin
                if (pixel_cnt_x == 15 && pixel_cnt_y == 15) 
                    next_state = (point_idx == 5) ? S_LHP_DECIDE : S_LHP_PICK;
                else 
                    next_state = S_LHP_CALC;
            end
            S_LHP_DECIDE: next_state = (best_vec_x == center_x && best_vec_y == center_y) ? S_SHP_PICK : S_LHP_PICK;
            S_SHP_PICK:   next_state = S_SHP_CALC;
            S_SHP_CALC:   begin
                if (pixel_cnt_x == 15 && pixel_cnt_y == 15) 
                    next_state = (point_idx == 3) ? S_DONE : S_SHP_PICK;
                else 
                    next_state = S_SHP_CALC;
            end
            S_DONE:       next_state = S_IDLE;
            default:      next_state = S_IDLE;
        endcase
    end

    // =========================================================
    // 3. 資料路徑 (Datapath)
    // =========================================================
    assign o_cur_x = pixel_cnt_x;
    assign o_cur_y = pixel_cnt_y;
    assign o_ref_x = 100 + cand_x + pixel_cnt_x; 
    assign o_ref_y = 100 + cand_y + pixel_cnt_y;

    always @(posedge clk or negedge rst_n) begin
        if (!rst_n) begin
            // [關鍵修正] 所有暫存器都要清零！
            center_x <= 0; center_y <= 0;
            cand_x <= 0;   cand_y <= 0;   // <--- 加入這行解藥！
            global_min_sad <= 16'hFFFF; 
            o_done <= 0;
            point_idx <= 0;
            pixel_cnt_x <= 0; pixel_cnt_y <= 0;
            o_mv_x <= 0; o_mv_y <= 0;
            current_accum_sad <= 0; // 順便把這個也清一下比較保險
        end else begin
            case (state)
                S_IDLE: begin
                    o_done <= 0;
                    center_x <= 0; center_y <= 0;
                    global_min_sad <= 16'hFFFF;
                    o_mv_x <= 0; o_mv_y <= 0;
                end

                S_INIT_00: begin
                    cand_x <= 0; cand_y <= 0; 
                    
                    if (pixel_cnt_x == 0 && pixel_cnt_y == 0) current_accum_sad <= abs_diff(i_cur_pixel, i_ref_pixel);
                    else current_accum_sad <= current_accum_sad + abs_diff(i_cur_pixel, i_ref_pixel);

                    if (pixel_cnt_x == 15) begin
                        pixel_cnt_x <= 0;
                        if (pixel_cnt_y == 15) begin
                            global_min_sad <= current_accum_sad + abs_diff(i_cur_pixel, i_ref_pixel);
                            best_vec_x <= 0; best_vec_y <= 0;
                            pixel_cnt_y <= 0;
                            point_idx <= 0; 
                        end else pixel_cnt_y <= pixel_cnt_y + 1;
                    end else pixel_cnt_x <= pixel_cnt_x + 1;
                end

                S_LHP_PICK: begin
                    pixel_cnt_x <= 0; pixel_cnt_y <= 0;
                    current_accum_sad <= 0;
                    case (point_idx)
                        0: begin cand_x <= center_x + 2; cand_y <= center_y + 0; end
                        1: begin cand_x <= center_x + 1; cand_y <= center_y + 2; end
                        2: begin cand_x <= center_x - 1; cand_y <= center_y + 2; end
                        3: begin cand_x <= center_x - 2; cand_y <= center_y + 0; end
                        4: begin cand_x <= center_x - 1; cand_y <= center_y - 2; end
                        5: begin cand_x <= center_x + 1; cand_y <= center_y - 2; end
                    endcase
                end

                S_LHP_CALC: begin
                    if (pixel_cnt_x == 0 && pixel_cnt_y == 0) current_accum_sad <= abs_diff(i_cur_pixel, i_ref_pixel);
                    else current_accum_sad <= current_accum_sad + abs_diff(i_cur_pixel, i_ref_pixel);

                    if (pixel_cnt_x == 15) begin
                        pixel_cnt_x <= 0;
                        if (pixel_cnt_y == 15) begin
                            pixel_cnt_y <= 0;
                            if ((current_accum_sad + abs_diff(i_cur_pixel, i_ref_pixel)) < global_min_sad) begin
                                global_min_sad <= current_accum_sad + abs_diff(i_cur_pixel, i_ref_pixel);
                                best_vec_x <= cand_x;
                                best_vec_y <= cand_y;
                            end
                            if (point_idx < 6) point_idx <= point_idx + 1;
                        end else pixel_cnt_y <= pixel_cnt_y + 1;
                    end else pixel_cnt_x <= pixel_cnt_x + 1;
                end

                S_LHP_DECIDE: begin
                    point_idx <= 0; 
                    if (best_vec_x != center_x || best_vec_y != center_y) begin
                        center_x <= best_vec_x;
                        center_y <= best_vec_y;
                    end
                end

                S_SHP_PICK: begin
                    pixel_cnt_x <= 0; pixel_cnt_y <= 0;
                    current_accum_sad <= 0;
                    case (point_idx)
                        0: begin cand_x <= center_x + 1; cand_y <= center_y + 0; end
                        1: begin cand_x <= center_x + 0; cand_y <= center_y + 1; end
                        2: begin cand_x <= center_x - 1; cand_y <= center_y + 0; end
                        3: begin cand_x <= center_x + 0; cand_y <= center_y - 1; end
                    endcase
                end

                S_SHP_CALC: begin
                    if (pixel_cnt_x == 0 && pixel_cnt_y == 0) current_accum_sad <= abs_diff(i_cur_pixel, i_ref_pixel);
                    else current_accum_sad <= current_accum_sad + abs_diff(i_cur_pixel, i_ref_pixel);

                    if (pixel_cnt_x == 15) begin
                        pixel_cnt_x <= 0;
                        if (pixel_cnt_y == 15) begin
                            pixel_cnt_y <= 0;
                            if ((current_accum_sad + abs_diff(i_cur_pixel, i_ref_pixel)) < global_min_sad) begin
                                global_min_sad <= current_accum_sad + abs_diff(i_cur_pixel, i_ref_pixel);
                                best_vec_x <= cand_x;
                                best_vec_y <= cand_y;
                            end
                            if (point_idx < 4) point_idx <= point_idx + 1;
                        end else pixel_cnt_y <= pixel_cnt_y + 1;
                    end else pixel_cnt_x <= pixel_cnt_x + 1;
                end

                S_DONE: begin
                    o_done <= 1;
                    o_mv_x <= best_vec_x;
                    o_mv_y <= best_vec_y;
                    o_min_sad <= global_min_sad;
                end
            endcase
        end
    end

endmodule

HEXBS/TestbenchforHEXBS.v
// ============================================================================
// File Name: tb_ME_HEXBS.v
// Description: 使用 XOR 圖案的測試平台，確保 (2,2) 是唯一解
//              (已修正：移除 SystemVerilog 語法，改用傳統 Verilog 以確保相容性)
// ============================================================================
`timescale 1ns/1ps

module tb_ME_HEXBS;

    reg clk, rst_n, i_start;
    wire [5:0]  o_cur_x, o_cur_y;
    reg  [7:0]  i_cur_pixel;
    wire [11:0] o_ref_x, o_ref_y;
    reg  [7:0]  i_ref_pixel;
    wire signed [5:0] o_mv_x, o_mv_y;
    wire [15:0] o_min_sad;
    wire        o_done;

    // 實例化你的硬體
    ME_HEXBS u_ME_HEXBS (
        .clk(clk), .rst_n(rst_n), .i_start(i_start),
        .o_cur_x(o_cur_x), .o_cur_y(o_cur_y), .i_cur_pixel(i_cur_pixel),
        .o_ref_x(o_ref_x), .o_ref_y(o_ref_y), .i_ref_pixel(i_ref_pixel),
        .o_mv_x(o_mv_x), .o_mv_y(o_mv_y), .o_min_sad(o_min_sad), .o_done(o_done)
    );

    // 時脈產生
    initial begin
        clk = 0;
        forever #5 clk = ~clk;
    end

    // --- 測試圖案 (XOR Pattern) ---
    always @(*) begin
        // Current: (x ^ y) * 8
        i_cur_pixel = (o_cur_x ^ o_cur_y) * 8; 
        
        // Reference: ((x-2) ^ (y-2)) * 8
        // 只有當 o_ref_x = x+2 且 o_ref_y = y+2 時，才會跟上面的 Current 一樣
        i_ref_pixel = ((o_ref_x - 100 - 2) ^ (o_ref_y - 100 - 2)) * 8; 
    end

    // --- 安全機制：超時強制結束 (Watchdog) ---
    // 這是第二條平行的時間線，如果跑太久 (100萬奈秒)，它會強制殺掉模擬
    initial begin
        #1000000; 
        $display("\nError: Simulation Timed Out! (硬體可能卡死或跑太慢)");
        $finish;
    end

    // --- 主測試流程 ---
    initial begin
        // 1. 初始化與重置
        rst_n = 1; i_start = 0;
        #20 rst_n = 0; 
        #20 rst_n = 1; 

        // 2. 啟動硬體
        #20 i_start = 1; 
        #10 i_start = 0;

        // 3. 等待硬體說「我做完了」(o_done 變成 1)
        wait(o_done == 1);
        
        // 4. 顯示結果並檢查
        $display("\n========================================");
        $display("HEXBS Simulation Results (XOR Pattern)");
        $display("Target MV: ( 2,  2)");
        $display("Actual MV: (%2d, %2d)", o_mv_x, o_mv_y);
        $display("Minimum SAD: %d", o_min_sad);
        $display("----------------------------------------");
        
        // 這裡用 === 是為了連不定值 (X) 都能比對出來
        if (o_mv_x === 6'sd2 && o_mv_y === 6'sd2 && o_min_sad === 0)
            $display("✅ PASS: 恭喜！完美命中 (2, 2)！");
        else
            $display("❌ FAIL: 結果不對，請檢查波形。");
        $display("========================================\n");

        // 5. 結束模擬 (這會順便把上面的計時炸彈關掉)
        #100 $finish;
    end

    // 產生波形檔
    initial begin
        $dumpfile("hexbs_wave.vcd");
        $dumpvars(0, tb_ME_HEXBS);
    end

endmodule

HEXBS/hexbs_wave.vcd
$date
	Thu Dec 11 09:43:38 2025
$end
$version
	Icarus Verilog
$end
$timescale
	1ps
$end
$scope module tb_ME_HEXBS $end
$var wire 12 ! o_ref_y [11:0] $end
$var wire 12 " o_ref_x [11:0] $end
$var wire 6 # o_mv_y [5:0] $end
$var wire 6 $ o_mv_x [5:0] $end
$var wire 16 % o_min_sad [15:0] $end
$var wire 1 & o_done $end
$var wire 6 ' o_cur_y [5:0] $end
$var wire 6 ( o_cur_x [5:0] $end
$var reg 1 ) clk $end
$var reg 8 * i_cur_pixel [7:0] $end
$var reg 8 + i_ref_pixel [7:0] $end
$var reg 1 , i_start $end
$var reg 1 - rst_n $end
$scope module u_ME_HEXBS $end
$var wire 1 ) clk $end
$var wire 8 . i_cur_pixel [7:0] $end
$var wire 8 / i_ref_pixel [7:0] $end
$var wire 1 , i_start $end
$var wire 1 - rst_n $end
$var wire 12 0 o_ref_y [11:0] $end
$var wire 12 1 o_ref_x [11:0] $end
$var wire 6 2 o_cur_y [5:0] $end
$var wire 6 3 o_cur_x [5:0] $end
$var parameter 4 4 S_DONE $end
$var parameter 4 5 S_IDLE $end
$var parameter 4 6 S_INIT_00 $end
$var parameter 4 7 S_LHP_CALC $end
$var parameter 4 8 S_LHP_DECIDE $end
$var parameter 4 9 S_LHP_PICK $end
$var parameter 4 : S_SHP_CALC $end
$var parameter 4 ; S_SHP_PICK $end
$var reg 6 < best_vec_x [5:0] $end
$var reg 6 = best_vec_y [5:0] $end
$var reg 6 > cand_x [5:0] $end
$var reg 6 ? cand_y [5:0] $end
$var reg 6 @ center_x [5:0] $end
$var reg 6 A center_y [5:0] $end
$var reg 16 B current_accum_sad [15:0] $end
$var reg 16 C global_min_sad [15:0] $end
$var reg 4 D next_state [3:0] $end
$var reg 1 & o_done $end
$var reg 16 E o_min_sad [15:0] $end
$var reg 6 F o_mv_x [5:0] $end
$var reg 6 G o_mv_y [5:0] $end
$var reg 5 H pixel_cnt_x [4:0] $end
$var reg 5 I pixel_cnt_y [4:0] $end
$var reg 3 J point_idx [2:0] $end
$var reg 4 K state [3:0] $end
$scope function abs_diff $end
$var reg 8 L a [7:0] $end
$var reg 8 M b [7:0] $end
$upscope $end
$upscope $end
$upscope $end
$enddefinitions $end
$comment Show the parameter values. $end
$dumpall
b101 ;
b110 :
b10 9
b100 8
b11 7
b1 6
b0 5
b111 4
$end
#0
$dumpvars
bx M
bx L
bx K
bx J
bx I
bx H
bx G
bx F
bx E
b0 D
bx C
bx B
bx A
bx @
bx ?
bx >
bx =
bx <
b0xxxxx 3
b0xxxxx 2
bx 1
bx 0
bx /
bx .
1-
0,
bx +
bx *
0)
b0xxxxx (
b0xxxxx '
x&
bx %
bx $
bx #
bx "
bx !
$end
#5000
b0 K
1)
#10000
0)
#15000
b0 #
b0 G
b0 $
b0 F
b1111111111111111 C
b0 A
b0 @
0&
1)
#20000
b0 +
b0 /
b0 *
b0 .
b0 B
b0 '
b0 2
b1100100 !
b1100100 0
b0 I
b0 (
b0 3
b1100100 "
b1100100 1
b0 H
b0 J
b0 ?
b0 >
0)
0-
#25000
1)
#30000
0)
#35000
1)
#40000
0)
1-
#45000
1)
#50000
0)
#55000
1)
#60000
b1 D
0)
1,
#65000
b1 K
1)
#70000
0)
0,
#75000
b1000 +
b1000 /
b1000 *
b1000 .
b1 (
b1 3
b1100101 "
b1100101 1
b1 H
b0 L
b0 M
1)
#80000
0)
#85000
b11110000 +
b11110000 /
b10000 *
b10000 .
b10 (
b10 3
b1100110 "
b1100110 1
b10 H
b1000 L
b1000 M
1)
#90000
0)
#95000
b11111000 +
b11111000 /
b11000 *
b11000 .
b11 (
b11 3
b1100111 "
b1100111 1
b11 H
b11100000 B
b10000 L
b11110000 M
1)
#100000
0)
#105000
b11100000 +
b11100000 /
b100000 *
b100000 .
b100 (
b100 3
b1101000 "
b1101000 1
b100 H
b111000000 B
b11000 L
b11111000 M
1)
#110000
0)
#115000
b11101000 +
b11101000 /
b101000 *
b101000 .
b101 (
b101 3
b1101001 "
b1101001 1
b101 H
b1010000000 B
b100000 L
b11100000 M
1)
#120000
0)
#125000
b11010000 +
b11010000 /
b110000 *
b110000 .
b110 (
b110 3
b1101010 "
b1101010 1
b110 H
b1101000000 B
b101000 L
b11101000 M
1)
#130000
0)
#135000
b11011000 +
b11011000 /
b111000 *
b111000 .
b111 (
b111 3
b1101011 "
b1101011 1
b111 H
b1111100000 B
b110000 L
b11010000 M
1)
#140000
0)
#145000
b11000000 +
b11000000 /
b1000000 *
b1000000 .
b1000 (
b1000 3
b1101100 "
b1101100 1
b1000 H
b10010000000 B
b111000 L
b11011000 M
1)
#150000
0)
#155000
b11001000 +
b11001000 /
b1001000 *
b1001000 .
b1001 (
b1001 3
b1101101 "
b1101101 1
b1001 H
b10100000000 B
b1000000 L
b11000000 M
1)
#160000
0)
#165000
b10110000 +
b10110000 /
b1010000 *
b1010000 .
b1010 (
b1010 3
b1101110 "
b1101110 1
b1010 H
b10110000000 B
b1001000 L
b11001000 M
1)
#170000
0)
#175000
b10111000 +
b10111000 /
b1011000 *
b1011000 .
b1011 (
b1011 3
b1101111 "
b1101111 1
b1011 H
b10111100000 B
b1010000 L
b10110000 M
1)
#180000
0)
#185000
b10100000 +
b10100000 /
b1100000 *
b1100000 .
b1100 (
b1100 3
b1110000 "
b1110000 1
b1100 H
b11001000000 B
b1011000 L
b10111000 M
1)
#190000
0)
#195000
b10101000 +
b10101000 /
b1101000 *
b1101000 .
b1101 (
b1101 3
b1110001 "
b1110001 1
b1101 H
b11010000000 B
b1100000 L
b10100000 M
1)
#200000
0)
#205000
b10010000 +
b10010000 /
b1110000 *
b1110000 .
b1110 (
b1110 3
b1110010 "
b1110010 1
b1110 H
b11011000000 B
b1101000 L
b10101000 M
1)
#210000
0)
#215000
b10011000 +
b10011000 /
b1111000 *
b1111000 .
b1111 (
b1111 3
b1110011 "
b1110011 1
b1111 H
b11011100000 B
b1110000 L
b10010000 M
1)
#220000
0)
#225000
b1000 +
b1000 /
b1000 *
b1000 .
b1 '
b1 2
b1100101 !
b1100101 0
b1 I
b0 (
b0 3
b1100100 "
b1100100 1
b0 H
b11100000000 B
b1111000 L
b10011000 M
1)
#230000
0)
#235000
b0 +
b0 /
b0 *
b0 .
b1 (
b1 3
b1100101 "
b1100101 1
b1 H
b1000 L
b1000 M
1)
#240000
0)
#245000
b11111000 +
b11111000 /
b11000 *
b11000 .
b10 (
b10 3
b1100110 "
b1100110 1
b10 H
b0 L
b0 M
1)
#250000
0)
#255000
b11110000 +
b11110000 /
b10000 *
b10000 .
b11 (
b11 3
b1100111 "
b1100111 1
b11 H
b11111100000 B
b11000 L
b11111000 M
1)
#260000
0)
#265000
b11101000 +
b11101000 /
b101000 *
b101000 .
b100 (
b100 3
b1101000 "
b1101000 1
b100 H
b100011000000 B
b10000 L
b11110000 M
1)
#270000
0)
#275000
b11100000 +
b11100000 /
b100000 *
b100000 .
b101 (
b101 3
b1101001 "
b1101001 1
b101 H
b100110000000 B
b101000 L
b11101000 M
1)
#280000
0)
#285000
b11011000 +
b11011000 /
b111000 *
b111000 .
b110 (
b110 3
b1101010 "
b1101010 1
b110 H
b101001000000 B
b100000 L
b11100000 M
1)
#290000
0)
#295000
b11010000 +
b11010000 /
b110000 *
b110000 .
b111 (
b111 3
b1101011 "
b1101011 1
b111 H
b101011100000 B
b111000 L
b11011000 M
1)
#300000
0)
#305000
b11001000 +
b11001000 /
b1001000 *
b1001000 .
b1000 (
b1000 3
b1101100 "
b1101100 1
b1000 H
b101110000000 B
b110000 L
b11010000 M
1)
#310000
0)
#315000
b11000000 +
b11000000 /
b1000000 *
b1000000 .
b1001 (
b1001 3
b1101101 "
b1101101 1
b1001 H
b110000000000 B
b1001000 L
b11001000 M
1)
#320000
0)
#325000
b10111000 +
b10111000 /
b1011000 *
b1011000 .
b1010 (
b1010 3
b1101110 "
b1101110 1
b1010 H
b110010000000 B
b1000000 L
b11000000 M
1)
#330000
0)
#335000
b10110000 +
b10110000 /
b1010000 *
b1010000 .
b1011 (
b1011 3
b1101111 "
b1101111 1
b1011 H
b110011100000 B
b1011000 L
b10111000 M
1)
#340000
0)
#345000
b10101000 +
b10101000 /
b1101000 *
b1101000 .
b1100 (
b1100 3
b1110000 "
b1110000 1
b1100 H
b110101000000 B
b1010000 L
b10110000 M
1)
#350000
0)
#355000
b10100000 +
b10100000 /
b1100000 *
b1100000 .
b1101 (
b1101 3
b1110001 "
b1110001 1
b1101 H
b110110000000 B
b1101000 L
b10101000 M
1)
#360000
0)
#365000
b10011000 +
b10011000 /
b1111000 *
b1111000 .
b1110 (
b1110 3
b1110010 "
b1110010 1
b1110 H
b110111000000 B
b1100000 L
b10100000 M
1)
#370000
0)
#375000
b10010000 +
b10010000 /
b1110000 *
b1110000 .
b1111 (
b1111 3
b1110011 "
b1110011 1
b1111 H
b110111100000 B
b1111000 L
b10011000 M
1)
#380000
0)
#385000
b11110000 +
b11110000 /
b10000 *
b10000 .
b10 '
b10 2
b1100110 !
b1100110 0
b10 I
b0 (
b0 3
b1100100 "
b1100100 1
b0 H
b111000000000 B
b1110000 L
b10010000 M
1)
#390000
0)
#395000
b11111000 +
b11111000 /
b11000 *
b11000 .
b1 (
b1 3
b1100101 "
b1100101 1
b1 H
b111011100000 B
b10000 L
b11110000 M
1)
#400000
0)
#405000
b0 +
b0 /
b0 *
b0 .
b10 (
b10 3
b1100110 "
b1100110 1
b10 H
b111111000000 B
b11000 L
b11111000 M
1)
#410000
0)
#415000
b1000 +
b1000 /
b1000 *
b1000 .
b11 (
b11 3
b1100111 "
b1100111 1
b11 H
b0 L
b0 M
1)
#420000
0)
#425000
b10000 +
b10000 /
b110000 *
b110000 .
b100 (
b100 3
b1101000 "
b1101000 1
b100 H
b1000 L
b1000 M
1)
#430000
0)
#435000
b11000 +
b11000 /
b111000 *
b111000 .
b101 (
b101 3
b1101001 "
b1101001 1
b101 H
b111111100000 B
b110000 L
b10000 M
1)
#440000
0)
#445000
b100000 +
b100000 /
b100000 *
b100000 .
b110 (
b110 3
b1101010 "
b1101010 1
b110 H
b1000000000000 B
b111000 L
b11000 M
1)
#450000
0)
#455000
b101000 +
b101000 /
b101000 *
b101000 .
b111 (
b111 3
b1101011 "
b1101011 1
b111 H
b100000 L
b100000 M
1)
#460000
0)
#465000
b110000 +
b110000 /
b1010000 *
b1010000 .
b1000 (
b1000 3
b1101100 "
b1101100 1
b1000 H
b101000 L
b101000 M
1)
#470000
0)
#475000
b111000 +
b111000 /
b1011000 *
b1011000 .
b1001 (
b1001 3
b1101101 "
b1101101 1
b1001 H
b1000000100000 B
b1010000 L
b110000 M
1)
#480000
0)
#485000
b1000000 +
b1000000 /
b1000000 *
b1000000 .
b1010 (
b1010 3
b1101110 "
b1101110 1
b1010 H
b1000001000000 B
b1011000 L
b111000 M
1)
#490000
0)
#495000
b1001000 +
b1001000 /
b1001000 *
b1001000 .
b1011 (
b1011 3
b1101111 "
b1101111 1
b1011 H
b1000000 L
b1000000 M
1)
#500000
0)
#505000
b1010000 +
b1010000 /
b1110000 *
b1110000 .
b1100 (
b1100 3
b1110000 "
b1110000 1
b1100 H
b1001000 L
b1001000 M
1)
#510000
0)
#515000
b1011000 +
b1011000 /
b1111000 *
b1111000 .
b1101 (
b1101 3
b1110001 "
b1110001 1
b1101 H
b1000001100000 B
b1110000 L
b1010000 M
1)
#520000
0)
#525000
b1100000 +
b1100000 /
b1100000 *
b1100000 .
b1110 (
b1110 3
b1110010 "
b1110010 1
b1110 H
b1000010000000 B
b1111000 L
b1011000 M
1)
#530000
0)
#535000
b1101000 +
b1101000 /
b1101000 *
b1101000 .
b1111 (
b1111 3
b1110011 "
b1110011 1
b1111 H
b1100000 L
b1100000 M
1)
#540000
0)
#545000
b11111000 +
b11111000 /
b11000 *
b11000 .
b11 '
b11 2
b1100111 !
b1100111 0
b11 I
b0 (
b0 3
b1100100 "
b1100100 1
b0 H
b1101000 L
b1101000 M
1)
#550000
0)
#555000
b11110000 +
b11110000 /
b10000 *
b10000 .
b1 (
b1 3
b1100101 "
b1100101 1
b1 H
b1000101100000 B
b11000 L
b11111000 M
1)
#560000
0)
#565000
b1000 +
b1000 /
b1000 *
b1000 .
b10 (
b10 3
b1100110 "
b1100110 1
b10 H
b1001001000000 B
b10000 L
b11110000 M
1)
#570000
0)
#575000
b0 +
b0 /
b0 *
b0 .
b11 (
b11 3
b1100111 "
b1100111 1
b11 H
b1000 L
b1000 M
1)
#580000
0)
#585000
b11000 +
b11000 /
b111000 *
b111000 .
b100 (
b100 3
b1101000 "
b1101000 1
b100 H
b0 L
b0 M
1)
#590000
0)
#595000
b10000 +
b10000 /
b110000 *
b110000 .
b101 (
b101 3
b1101001 "
b1101001 1
b101 H
b1001001100000 B
b111000 L
b11000 M
1)
#600000
0)
#605000
b101000 +
b101000 /
b101000 *
b101000 .
b110 (
b110 3
b1101010 "
b1101010 1
b110 H
b1001010000000 B
b110000 L
b10000 M
1)
#610000
0)
#615000
b100000 +
b100000 /
b100000 *
b100000 .
b111 (
b111 3
b1101011 "
b1101011 1
b111 H
b101000 L
b101000 M
1)
#620000
0)
#625000
b111000 +
b111000 /
b1011000 *
b1011000 .
b1000 (
b1000 3
b1101100 "
b1101100 1
b1000 H
b100000 L
b100000 M
1)
#630000
0)
#635000
b110000 +
b110000 /
b1010000 *
b1010000 .
b1001 (
b1001 3
b1101101 "
b1101101 1
b1001 H
b1001010100000 B
b1011000 L
b111000 M
1)
#640000
0)
#645000
b1001000 +
b1001000 /
b1001000 *
b1001000 .
b1010 (
b1010 3
b1101110 "
b1101110 1
b1010 H
b1001011000000 B
b1010000 L
b110000 M
1)
#650000
0)
#655000
b1000000 +
b1000000 /
b1000000 *
b1000000 .
b1011 (
b1011 3
b1101111 "
b1101111 1
b1011 H
b1001000 L
b1001000 M
1)
#660000
0)
#665000
b1011000 +
b1011000 /
b1111000 *
b1111000 .
b1100 (
b1100 3
b1110000 "
b1110000 1
b1100 H
b1000000 L
b1000000 M
1)
#670000
0)
#675000
b1010000 +
b1010000 /
b1110000 *
b1110000 .
b1101 (
b1101 3
b1110001 "
b1110001 1
b1101 H
b1001011100000 B
b1111000 L
b1011000 M
1)
#680000
0)
#685000
b1101000 +
b1101000 /
b1101000 *
b1101000 .
b1110 (
b1110 3
b1110010 "
b1110010 1
b1110 H
b1001100000000 B
b1110000 L
b1010000 M
1)
#690000
0)
#695000
b1100000 +
b1100000 /
b1100000 *
b1100000 .
b1111 (
b1111 3
b1110011 "
b1110011 1
b1111 H
b1101000 L
b1101000 M
1)
#700000
0)
#705000
b11100000 +
b11100000 /
b100000 *
b100000 .
b100 '
b100 2
b1101000 !
b1101000 0
b100 I
b0 (
b0 3
b1100100 "
b1100100 1
b0 H
b1100000 L
b1100000 M
1)
#710000
0)
#715000
b11101000 +
b11101000 /
b101000 *
b101000 .
b1 (
b1 3
b1100101 "
b1100101 1
b1 H
b1001111000000 B
b100000 L
b11100000 M
1)
#720000
0)
#725000
b10000 +
b10000 /
b110000 *
b110000 .
b10 (
b10 3
b1100110 "
b1100110 1
b10 H
b1010010000000 B
b101000 L
b11101000 M
1)
#730000
0)
#735000
b11000 +
b11000 /
b111000 *
b111000 .
b11 (
b11 3
b1100111 "
b1100111 1
b11 H
b1010010100000 B
b110000 L
b10000 M
1)
#740000
0)
#745000
b0 +
b0 /
b0 *
b0 .
b100 (
b100 3
b1101000 "
b1101000 1
b100 H
b1010011000000 B
b111000 L
b11000 M
1)
#750000
0)
#755000
b1000 +
b1000 /
b1000 *
b1000 .
b101 (
b101 3
b1101001 "
b1101001 1
b101 H
b0 L
b0 M
1)
#760000
0)
#765000
b110000 +
b110000 /
b10000 *
b10000 .
b110 (
b110 3
b1101010 "
b1101010 1
b110 H
b1000 L
b1000 M
1)
#770000
0)
#775000
b111000 +
b111000 /
b11000 *
b11000 .
b111 (
b111 3
b1101011 "
b1101011 1
b111 H
b1010011100000 B
b10000 L
b110000 M
1)
#780000
0)
#785000
b100000 +
b100000 /
b1100000 *
b1100000 .
b1000 (
b1000 3
b1101100 "
b1101100 1
b1000 H
b1010100000000 B
b11000 L
b111000 M
1)
#790000
0)
#795000
b101000 +
b101000 /
b1101000 *
b1101000 .
b1001 (
b1001 3
b1101101 "
b1101101 1
b1001 H
b1010101000000 B
b1100000 L
b100000 M
1)
#800000
0)
#805000
b1010000 +
b1010000 /
b1110000 *
b1110000 .
b1010 (
b1010 3
b1101110 "
b1101110 1
b1010 H
b1010110000000 B
b1101000 L
b101000 M
1)
#810000
0)
#815000
b1011000 +
b1011000 /
b1111000 *
b1111000 .
b1011 (
b1011 3
b1101111 "
b1101111 1
b1011 H
b1010110100000 B
b1110000 L
b1010000 M
1)
#820000
0)
#825000
b1000000 +
b1000000 /
b1000000 *
b1000000 .
b1100 (
b1100 3
b1110000 "
b1110000 1
b1100 H
b1010111000000 B
b1111000 L
b1011000 M
1)
#830000
0)
#835000
b1001000 +
b1001000 /
b1001000 *
b1001000 .
b1101 (
b1101 3
b1110001 "
b1110001 1
b1101 H
b1000000 L
b1000000 M
1)
#840000
0)
#845000
b1110000 +
b1110000 /
b1010000 *
b1010000 .
b1110 (
b1110 3
b1110010 "
b1110010 1
b1110 H
b1001000 L
b1001000 M
1)
#850000
0)
#855000
b1111000 +
b1111000 /
b1011000 *
b1011000 .
b1111 (
b1111 3
b1110011 "
b1110011 1
b1111 H
b1010111100000 B
b1010000 L
b1110000 M
1)
#860000
0)
#865000
b11101000 +
b11101000 /
b101000 *
b101000 .
b101 '
b101 2
b1101001 !
b1101001 0
b101 I
b0 (
b0 3
b1100100 "
b1100100 1
b0 H
b1011000000000 B
b1011000 L
b1111000 M
1)
#870000
0)
#875000
b11100000 +
b11100000 /
b100000 *
b100000 .
b1 (
b1 3
b1100101 "
b1100101 1
b1 H
b1011011000000 B
b101000 L
b11101000 M
1)
#880000
0)
#885000
b11000 +
b11000 /
b111000 *
b111000 .
b10 (
b10 3
b1100110 "
b1100110 1
b10 H
b1011110000000 B
b100000 L
b11100000 M
1)
#890000
0)
#895000
b10000 +
b10000 /
b110000 *
b110000 .
b11 (
b11 3
b1100111 "
b1100111 1
b11 H
b1011110100000 B
b111000 L
b11000 M
1)
#900000
0)
#905000
b1000 +
b1000 /
b1000 *
b1000 .
b100 (
b100 3
b1101000 "
b1101000 1
b100 H
b1011111000000 B
b110000 L
b10000 M
1)
#910000
0)
#915000
b0 +
b0 /
b0 *
b0 .
b101 (
b101 3
b1101001 "
b1101001 1
b101 H
b1000 L
b1000 M
1)
#920000
0)
#925000
b111000 +
b111000 /
b11000 *
b11000 .
b110 (
b110 3
b1101010 "
b1101010 1
b110 H
b0 L
b0 M
1)
#930000
0)
#935000
b110000 +
b110000 /
b10000 *
b10000 .
b111 (
b111 3
b1101011 "
b1101011 1
b111 H
b1011111100000 B
b11000 L
b111000 M
1)
#940000
0)
#945000
b101000 +
b101000 /
b1101000 *
b1101000 .
b1000 (
b1000 3
b1101100 "
b1101100 1
b1000 H
b1100000000000 B
b10000 L
b110000 M
1)
#950000
0)
