HEXBS/me_hexbs_top.v
// ============================================================================
// File Name: ME_HEXBS.v
// Author: HSUN's AI Assistant
// Description: Hexagon-Based Search (HEXBS) Motion Estimation Accelerator
//              Fixed: Added reset logic for cand_x/cand_y to prevent 'X' propagation
// ============================================================================

module ME_HEXBS (
    input  wire         clk,        // 時脈
    input  wire         rst_n,      // 重置訊號 (低電位重置)
    input  wire         i_start,    // 啟動訊號

    // --- 虛擬記憶體介面 ---
    output wire [5:0]   o_cur_x,    
    output wire [5:0]   o_cur_y,    
    input  wire [7:0]   i_cur_pixel,

    output wire [11:0]  o_ref_x,    
    output wire [11:0]  o_ref_y,    
    input  wire [7:0]   i_ref_pixel,

    // --- 輸出結果 ---
    output reg  signed [5:0] o_mv_x,    
    output reg  signed [5:0] o_mv_y,    
    output reg  [15:0]       o_min_sad, 
    output reg               o_done     
);

    // =========================================================
    // 1. 參數與變數
    // =========================================================
    localparam S_IDLE       = 4'd0; 
    localparam S_INIT_00    = 4'd1; 
    localparam S_LHP_PICK   = 4'd2; 
    localparam S_LHP_CALC   = 4'd3; 
    localparam S_LHP_DECIDE = 4'd4; 
    localparam S_SHP_PICK   = 4'd5; 
    localparam S_SHP_CALC   = 4'd6; 
    localparam S_DONE       = 4'd7; 

    reg [3:0]  state, next_state;

    // 搜尋中心與候選點
    reg signed [5:0] center_x, center_y;    
    reg signed [5:0] cand_x, cand_y;        // [Bug Fix] 這裡原本沒 Reset
    
    reg [15:0] global_min_sad;              
    reg signed [5:0] best_vec_x, best_vec_y;

    reg [4:0]  pixel_cnt_x; 
    reg [4:0]  pixel_cnt_y; 
    reg [15:0] current_accum_sad; 

    reg [2:0]  point_idx;   

    // =========================================================
    // 2. 函數與 FSM
    // =========================================================
    function [7:0] abs_diff;
        input [7:0] a, b;
        begin
            abs_diff = (a > b) ? (a - b) : (b - a);
        end
    endfunction

    always @(posedge clk or negedge rst_n) begin
        if (!rst_n) state <= S_IDLE;
        else        state <= next_state;
    end

    always @(*) begin
        case (state)
            S_IDLE:       next_state = i_start ? S_INIT_00 : S_IDLE;
            S_INIT_00:    next_state = (pixel_cnt_x == 15 && pixel_cnt_y == 15) ? S_LHP_PICK : S_INIT_00;
            S_LHP_PICK:   next_state = S_LHP_CALC;
            S_LHP_CALC:   begin
                if (pixel_cnt_x == 15 && pixel_cnt_y == 15) 
                    next_state = (point_idx == 5) ? S_LHP_DECIDE : S_LHP_PICK;
                else 
                    next_state = S_LHP_CALC;
            end
            S_LHP_DECIDE: next_state = (best_vec_x == center_x && best_vec_y == center_y) ? S_SHP_PICK : S_LHP_PICK;
            S_SHP_PICK:   next_state = S_SHP_CALC;
            S_SHP_CALC:   begin
                if (pixel_cnt_x == 15 && pixel_cnt_y == 15) 
                    next_state = (point_idx == 3) ? S_DONE : S_SHP_PICK;
                else 
                    next_state = S_SHP_CALC;
            end
            S_DONE:       next_state = S_IDLE;
            default:      next_state = S_IDLE;
        endcase
    end

    // =========================================================
    // 3. 資料路徑 (Datapath)
    // =========================================================
    assign o_cur_x = pixel_cnt_x;
    assign o_cur_y = pixel_cnt_y;
    assign o_ref_x = 100 + cand_x + pixel_cnt_x; 
    assign o_ref_y = 100 + cand_y + pixel_cnt_y;

    always @(posedge clk or negedge rst_n) begin
        if (!rst_n) begin
            // [關鍵修正] 所有暫存器都要清零！
            center_x <= 0; center_y <= 0;
            cand_x <= 0;   cand_y <= 0;   // <--- 加入這行解藥！
            global_min_sad <= 16'hFFFF; 
            o_done <= 0;
            point_idx <= 0;
            pixel_cnt_x <= 0; pixel_cnt_y <= 0;
            o_mv_x <= 0; o_mv_y <= 0;
            current_accum_sad <= 0; // 順便把這個也清一下比較保險
        end else begin
            case (state)
                S_IDLE: begin
                    o_done <= 0;
                    center_x <= 0; center_y <= 0;
                    global_min_sad <= 16'hFFFF;
                    o_mv_x <= 0; o_mv_y <= 0;
                end

                S_INIT_00: begin
                    cand_x <= 0; cand_y <= 0; 
                    
                    if (pixel_cnt_x == 0 && pixel_cnt_y == 0) current_accum_sad <= abs_diff(i_cur_pixel, i_ref_pixel);
                    else current_accum_sad <= current_accum_sad + abs_diff(i_cur_pixel, i_ref_pixel);

                    if (pixel_cnt_x == 15) begin
                        pixel_cnt_x <= 0;
                        if (pixel_cnt_y == 15) begin
                            global_min_sad <= current_accum_sad + abs_diff(i_cur_pixel, i_ref_pixel);
                            best_vec_x <= 0; best_vec_y <= 0;
                            pixel_cnt_y <= 0;
                            point_idx <= 0; 
                        end else pixel_cnt_y <= pixel_cnt_y + 1;
                    end else pixel_cnt_x <= pixel_cnt_x + 1;
                end

                S_LHP_PICK: begin
                    pixel_cnt_x <= 0; pixel_cnt_y <= 0;
                    current_accum_sad <= 0;
                    case (point_idx)
                        0: begin cand_x <= center_x + 2; cand_y <= center_y + 0; end
                        1: begin cand_x <= center_x + 1; cand_y <= center_y + 2; end
                        2: begin cand_x <= center_x - 1; cand_y <= center_y + 2; end
                        3: begin cand_x <= center_x - 2; cand_y <= center_y + 0; end
                        4: begin cand_x <= center_x - 1; cand_y <= center_y - 2; end
                        5: begin cand_x <= center_x + 1; cand_y <= center_y - 2; end
                    endcase
                end

                S_LHP_CALC: begin
                    if (pixel_cnt_x == 0 && pixel_cnt_y == 0) current_accum_sad <= abs_diff(i_cur_pixel, i_ref_pixel);
                    else current_accum_sad <= current_accum_sad + abs_diff(i_cur_pixel, i_ref_pixel);

                    if (pixel_cnt_x == 15) begin
                        pixel_cnt_x <= 0;
                        if (pixel_cnt_y == 15) begin
                            pixel_cnt_y <= 0;
                            if ((current_accum_sad + abs_diff(i_cur_pixel, i_ref_pixel)) < global_min_sad) begin
                                global_min_sad <= current_accum_sad + abs_diff(i_cur_pixel, i_ref_pixel);
                                best_vec_x <= cand_x;
                                best_vec_y <= cand_y;
                            end
                            if (point_idx < 6) point_idx <= point_idx + 1;
                        end else pixel_cnt_y <= pixel_cnt_y + 1;
                    end else pixel_cnt_x <= pixel_cnt_x + 1;
                end

                S_LHP_DECIDE: begin
                    point_idx <= 0; 
                    if (best_vec_x != center_x || best_vec_y != center_y) begin
                        center_x <= best_vec_x;
                        center_y <= best_vec_y;
                    end
                end

                S_SHP_PICK: begin
                    pixel_cnt_x <= 0; pixel_cnt_y <= 0;
                    current_accum_sad <= 0;
                    case (point_idx)
                        0: begin cand_x <= center_x + 1; cand_y <= center_y + 0; end
                        1: begin cand_x <= center_x + 0; cand_y <= center_y + 1; end
                        2: begin cand_x <= center_x - 1; cand_y <= center_y + 0; end
                        3: begin cand_x <= center_x + 0; cand_y <= center_y - 1; end
                    endcase
                end

                S_SHP_CALC: begin
                    if (pixel_cnt_x == 0 && pixel_cnt_y == 0) current_accum_sad <= abs_diff(i_cur_pixel, i_ref_pixel);
                    else current_accum_sad <= current_accum_sad + abs_diff(i_cur_pixel, i_ref_pixel);

                    if (pixel_cnt_x == 15) begin
                        pixel_cnt_x <= 0;
                        if (pixel_cnt_y == 15) begin
                            pixel_cnt_y <= 0;
                            if ((current_accum_sad + abs_diff(i_cur_pixel, i_ref_pixel)) < global_min_sad) begin
                                global_min_sad <= current_accum_sad + abs_diff(i_cur_pixel, i_ref_pixel);
                                best_vec_x <= cand_x;
                                best_vec_y <= cand_y;
                            end
                            if (point_idx < 4) point_idx <= point_idx + 1;
                        end else pixel_cnt_y <= pixel_cnt_y + 1;
                    end else pixel_cnt_x <= pixel_cnt_x + 1;
                end

                S_DONE: begin
                    o_done <= 1;
                    o_mv_x <= best_vec_x;
                    o_mv_y <= best_vec_y;
                    o_min_sad <= global_min_sad;
                end
            endcase
        end
    end

endmodule

HEXBS/TestbenchforHEXBS.v
// ============================================================================
// File Name: tb_ME_HEXBS.v
// Author: HSUN's AI Assistant
// Description: Testbench for ME_HEXBS
//              模擬環境，產生時脈並給予假資料
// ============================================================================
`timescale 1ns/1ps

module tb_ME_HEXBS;

    // 1. 訊號宣告
    reg clk;
    reg rst_n;
    reg i_start;

    // 連接到 DUT (Device Under Test) 的線
    wire [5:0]  o_cur_x, o_cur_y;
    reg  [7:0]  i_cur_pixel;
    
    wire [11:0] o_ref_x, o_ref_y;
    reg  [7:0]  i_ref_pixel;

    wire signed [5:0] o_mv_x, o_mv_y;
    wire [15:0] o_min_sad;
    wire        o_done;

    // 2. 實例化 (Instantiate) 你的硬體
    ME_HEXBS u_ME_HEXBS (
        .clk(clk),
        .rst_n(rst_n),
        .i_start(i_start),
        .o_cur_x(o_cur_x),
        .o_cur_y(o_cur_y),
        .i_cur_pixel(i_cur_pixel),
        .o_ref_x(o_ref_x),
        .o_ref_y(o_ref_y),
        .i_ref_pixel(i_ref_pixel),
        .o_mv_x(o_mv_x),
        .o_mv_y(o_mv_y),
        .o_min_sad(o_min_sad),
        .o_done(o_done)
    );

    // 3. 產生時脈 (Clock Generation) - 10ns 週期
    initial begin
        clk = 0;
        forever #5 clk = ~clk;
    end

    // 4. 模擬記憶體行為 (Mock Memory)
    // 當硬體改變地址時，我們給它一點假資料
    always @(*) begin
        // 簡單製造一個 Pattern：
        // 假設 Current Block 是一個漸層
        i_cur_pixel = o_cur_x + o_cur_y; 
        
        // 假設 Reference Frame 也是類似漸層，但在 (2,2) 的位置最像
        // 這樣我們預期 Motion Vector 應該會算出 (2,2) 或者接近的值
        i_ref_pixel = (o_ref_x - 100 - 2) + (o_ref_y - 100 - 2); 
    end

    // 5. 測試流程 (Test Stimulus)
    initial begin
        // 5.1 初始化
        rst_n = 1;
        i_start = 0;
        
        // 5.2 重置
        #20 rst_n = 0; // 按下 Reset
        #20 rst_n = 1; // 放開 Reset

        // 5.3 啟動運算
        #20 i_start = 1; // 告訴硬體開始跑
        #10 i_start = 0;

        // 5.4 等待完成
        wait(o_done == 1);
        
        // 5.5 顯示結果
        $display("========================================");
        $display("HEXBS Simulation Finished!");
        $display("Result Motion Vector: (%d, %d)", o_mv_x, o_mv_y);
        $display("Minimum SAD: %d", o_min_sad);
        $display("========================================");

        #100 $finish;
    end

    // 產生波形檔 (給 Vivado 或 Verdi 看)
    initial begin
        $dumpfile("hexbs_wave.vcd");
        $dumpvars(0, tb_ME_HEXBS);
    end

endmodule

HEXBS/hexbs_wave.vcd
$date
	Thu Dec 11 15:51:29 2025
$end
$version
	Icarus Verilog
$end
$timescale
	1ps
$end
$scope module tb_ME_HEXBS $end
$var wire 12 ! o_ref_y [11:0] $end
$var wire 12 " o_ref_x [11:0] $end
$var wire 6 # o_mv_y [5:0] $end
$var wire 6 $ o_mv_x [5:0] $end
$var wire 16 % o_min_sad [15:0] $end
$var wire 1 & o_done $end
$var wire 6 ' o_cur_y [5:0] $end
$var wire 6 ( o_cur_x [5:0] $end
$var reg 1 ) clk $end
$var reg 8 * i_cur_pixel [7:0] $end
$var reg 8 + i_ref_pixel [7:0] $end
$var reg 1 , i_start $end
$var reg 1 - rst_n $end
$scope module u_ME_HEXBS $end
$var wire 1 ) clk $end
$var wire 8 . i_cur_pixel [7:0] $end
$var wire 8 / i_ref_pixel [7:0] $end
$var wire 1 , i_start $end
$var wire 1 - rst_n $end
$var wire 12 0 o_ref_y [11:0] $end
$var wire 12 1 o_ref_x [11:0] $end
$var wire 6 2 o_cur_y [5:0] $end
$var wire 6 3 o_cur_x [5:0] $end
$var parameter 4 4 S_DONE $end
$var parameter 4 5 S_IDLE $end
$var parameter 4 6 S_INIT_00 $end
$var parameter 4 7 S_LHP_CALC $end
$var parameter 4 8 S_LHP_DECIDE $end
$var parameter 4 9 S_LHP_PICK $end
$var parameter 4 : S_SHP_CALC $end
$var parameter 4 ; S_SHP_PICK $end
$var reg 6 < best_vec_x [5:0] $end
$var reg 6 = best_vec_y [5:0] $end
$var reg 6 > cand_x [5:0] $end
$var reg 6 ? cand_y [5:0] $end
$var reg 6 @ center_x [5:0] $end
$var reg 6 A center_y [5:0] $end
$var reg 16 B current_accum_sad [15:0] $end
$var reg 16 C global_min_sad [15:0] $end
$var reg 4 D next_state [3:0] $end
$var reg 1 & o_done $end
$var reg 16 E o_min_sad [15:0] $end
$var reg 6 F o_mv_x [5:0] $end
$var reg 6 G o_mv_y [5:0] $end
$var reg 5 H pixel_cnt_x [4:0] $end
$var reg 5 I pixel_cnt_y [4:0] $end
$var reg 3 J point_idx [2:0] $end
$var reg 4 K state [3:0] $end
$scope function abs_diff $end
$var reg 8 L a [7:0] $end
$var reg 8 M b [7:0] $end
$upscope $end
$upscope $end
$upscope $end
$enddefinitions $end
$comment Show the parameter values. $end
$dumpall
b101 ;
b110 :
b10 9
b100 8
b11 7
b1 6
b0 5
b111 4
$end
#0
$dumpvars
bx M
bx L
bx K
bx J
bx I
bx H
bx G
bx F
bx E
b0 D
bx C
bx B
bx A
bx @
bx ?
bx >
bx =
bx <
b0xxxxx 3
b0xxxxx 2
bx 1
bx 0
bx /
bx .
1-
0,
bx +
bx *
0)
b0xxxxx (
b0xxxxx '
x&
bx %
bx $
bx #
bx "
bx !
$end
#5000
b0 K
1)
#10000
0)
#15000
b0 #
b0 G
b0 $
b0 F
b1111111111111111 C
b0 A
b0 @
0&
1)
#20000
b0 +
b0 /
b0 *
b0 .
b0 B
b0 '
b0 2
b1100100 !
b1100100 0
b0 I
b0 (
b0 3
b1100100 "
b1100100 1
b0 H
b0 J
b0 ?
b0 >
0)
0-
#25000
1)
#30000
0)
#35000
1)
#40000
0)
1-
#45000
1)
#50000
0)
#55000
1)
#60000
b1 D
0)
1,
#65000
b1 K
1)
#70000
0)
0,
#75000
b1000 +
b1000 /
b1000 *
b1000 .
b1 (
b1 3
b1100101 "
b1100101 1
b1 H
b0 L
b0 M
1)
#80000
0)
#85000
b11110000 +
b11110000 /
b10000 *
b10000 .
b10 (
b10 3
b1100110 "
b1100110 1
b10 H
b1000 L
b1000 M
1)
#90000
0)
#95000
b11111000 +
b11111000 /
b11000 *
b11000 .
b11 (
b11 3
b1100111 "
b1100111 1
b11 H
b11100000 B
b10000 L
b11110000 M
1)
#100000
0)
#105000
b11100000 +
b11100000 /
b100000 *
b100000 .
b100 (
b100 3
b1101000 "
b1101000 1
b100 H
b111000000 B
b11000 L
b11111000 M
1)
#110000
0)
#115000
b11101000 +
b11101000 /
b101000 *
b101000 .
b101 (
b101 3
b1101001 "
b1101001 1
b101 H
b1010000000 B
b100000 L
b11100000 M
1)
